lomefaire/__init__.py
lomefaire/main.py
lomefaire-0.1.0.dist-info/METADATA
lomefaire-0.1.0.dist-info/WHEEL
lomefaire-0.1.0.dist-info/top_level.txt
lomefaire-0.1.0.dist-info/RECORD
