Metadata-Version: 2.1
Name: lomefaire
Version: 0.1.0
Summary: Test
Author: lomefaire
Author-email: lomefaire@gmail.com
Classifier: Programming Language :: Python :: 3
Classifier: License :: OSI Approved :: MIT License
Classifier: Operating System :: OS Independent
Requires-Python: >=3.12
Requires-Dist: numpy
Requires-Dist: opencv-python
